de/__init__.py
de/pack.py
depack-0.0.2.dist-info/METADATA
depack-0.0.2.dist-info/WHEEL
depack-0.0.2.dist-info/entry_points.txt
depack-0.0.2.dist-info/top_level.txt
depack-0.0.2.dist-info/RECORD
